{"api_batch.md":"CHvYU5zN","api_component.md":"O2AkGIoW","api_computed.md":"IhEhvzg2","api_effect.md":"DKXEvXhx","api_renderer.md":"CtSEdPWu","api_signal.md":"CxPmKz-E","api_streaming.md":"BO0L2PsR","blog_ai-native-development.md":"bdSb5BtC","blog_fine-grained-reactivity.md":"C501VTHQ","blog_index.md":"m_AioRmv","blog_v0.5.0-release.md":"7v0tscx4","examples_ai-integration.md":"YfXgGPBl","examples_basic.md":"CgLoPfak","examples_counter.md":"BaNu0H35","examples_todo.md":"y1haN_l7","guide_ai-native.md":"DjInV1jq","guide_components.md":"DCiPW8En","guide_core-concepts.md":"CIrL1_up","guide_getting-started.md":"CeMp2rTe","guide_migration-from-react.md":"CPIPvPii","guide_migration-from-vue.md":"CjDZga1z","guide_quick-start.md":"CZepJulL","guide_reactivity.md":"Dbjf9RaR","guide_ssr.md":"B6a3b9DJ","guide_streaming.md":"DYs7EpJ0","guide_why-qore.md":"BSm3Jejg","index.md":"DCjzTowh","readme.md":"BmI6Ah-8"}
